README
setup.py
notossh/__init__.py
notossh/notossh.py
notossh.egg-info/PKG-INFO
notossh.egg-info/SOURCES.txt
notossh.egg-info/dependency_links.txt
notossh.egg-info/entry_points.txt
notossh.egg-info/not-zip-safe
notossh.egg-info/requires.txt
notossh.egg-info/top_level.txt