Metadata-Version: 1.1
Name: notossh
Version: 1.0
Summary: NOTifications Over SSH
Home-page: http://m0g.net/notossh/
Author: Bernard `Guyzmo` Pratz
Author-email: notossh@m0g.net
License: WTFPL
Keywords: ssh irc notifications growl libnotify irssi erc daemon
Platform: UNKNOWN
Classifier: Environment :: Console
Classifier: Topic :: Communications :: Chat :: Internet Relay Chat
Classifier: Environment :: MacOS X
Classifier: Environment :: X11 Applications
Classifier: Topic :: Text Editors :: Emacs
